lmcache/__init__.py
lmcache/_version.py
lmcache/c_ops.cpython-310-x86_64-linux-gnu.so
lmcache/cache_engine.py
lmcache/config.py
lmcache/connections.py
lmcache/logging.py
lmcache/observability.py
lmcache/protocol.py
lmcache/usage_context.py
lmcache/utils.py
lmcache/blend/__init__.py
lmcache/blend/executor.py
lmcache/blend/interfaces.py
lmcache/blend/retriever.py
lmcache/experimental/__init__.py
lmcache/experimental/cache_engine.py
lmcache/experimental/cache_interface.py
lmcache/experimental/config.py
lmcache/experimental/gpu_connector.py
lmcache/experimental/memory_management.py
lmcache/experimental/protocol.py
lmcache/experimental/token_database.py
lmcache/experimental/api_server/__init__.py
lmcache/experimental/api_server/__main__.py
lmcache/experimental/cache_controller/__init__.py
lmcache/experimental/cache_controller/controller_manager.py
lmcache/experimental/cache_controller/executor.py
lmcache/experimental/cache_controller/message.py
lmcache/experimental/cache_controller/rpc_utils.py
lmcache/experimental/cache_controller/worker.py
lmcache/experimental/cache_controller/controllers/__init__.py
lmcache/experimental/cache_controller/controllers/kv_controller.py
lmcache/experimental/cache_controller/controllers/registration_controller.py
lmcache/experimental/distributed_server/__init__.py
lmcache/experimental/distributed_server/abstract_server.py
lmcache/experimental/distributed_server/naive_server.py
lmcache/experimental/lookup_server/__init__.py
lmcache/experimental/lookup_server/abstract_server.py
lmcache/experimental/lookup_server/redis_server.py
lmcache/experimental/server/__init__.py
lmcache/experimental/server/__main__.py
lmcache/experimental/server/utils.py
lmcache/experimental/server/storage_backend/__init__.py
lmcache/experimental/server/storage_backend/abstract_backend.py
lmcache/experimental/server/storage_backend/local_backend.py
lmcache/experimental/storage_backend/__init__.py
lmcache_test_test-1.0.5.dist-info/METADATA
lmcache_test_test-1.0.5.dist-info/WHEEL
lmcache_test_test-1.0.5.dist-info/entry_points.txt
lmcache_test_test-1.0.5.dist-info/top_level.txt
lmcache_test_test-1.0.5.dist-info/RECORD
lmcache_test_test-1.0.5.dist-info/licenses/LICENSE
