Metadata-Version: 2.4
Name: lmcache_test_test
Version: 1.0.5
Summary: LMCache: prefill your long contexts only once
Author: LMCache team
Author-email: lmcacheteam@gmail.com
License: Apache-2.0
Classifier: Development Status :: 3 - Alpha
Classifier: Environment :: GPU
Classifier: Programming Language :: Python :: 3
Classifier: License :: OSI Approved :: Apache Software License
Requires-Python: >=3.10
License-File: LICENSE
Requires-Dist: torch==2.6.0
Requires-Dist: numpy==1.26.4
Requires-Dist: aiofiles
Requires-Dist: pyyaml
Requires-Dist: redis
Requires-Dist: nvtx
Requires-Dist: safetensors
Requires-Dist: transformers
Requires-Dist: psutil
Requires-Dist: aiohttp
Requires-Dist: sortedcontainers
Requires-Dist: prometheus_client
Requires-Dist: infinistore
Requires-Dist: msgspec
Requires-Dist: pyzmq
Requires-Dist: transformers
Dynamic: author
Dynamic: author-email
Dynamic: classifier
Dynamic: description
Dynamic: description-content-type
Dynamic: license
Dynamic: license-file
Dynamic: requires-dist
Dynamic: requires-python
Dynamic: summary
